typetools/__init__.py
typetools/_broadtypes.py
typetools/_descriptor.py
typetools/_test_typetools.py
typetools/_typed.py
typetools/_types.py
typetools/broadtypes.py
typetools/descriptor.py
typetools/typed.py
typetools/types.py
TypeTools-2.0.0.dist-info/METADATA
TypeTools-2.0.0.dist-info/WHEEL
TypeTools-2.0.0.dist-info/top_level.txt
TypeTools-2.0.0.dist-info/RECORD
