Metadata-Version: 2.1
Name: TypeTools
Version: 2.0.0
Summary: Help with enforcing types.
Home-page: UNKNOWN
Author: Alan Bagel
Author-email: jiuprogrammer@gmail.com
License: UNKNOWN
Platform: UNKNOWN
